mensajes/__init__.py
mensajes/adios/__init__.py
mensajes/adios/despedidas.py
mensajes/hola/__init__.py
mensajes/hola/saludos.py
tests/__init__.py
tests/test_hola.py
Mensajes_SPARTAN_TANIKAZE-1.5.dist-info/LICENSE
Mensajes_SPARTAN_TANIKAZE-1.5.dist-info/METADATA
Mensajes_SPARTAN_TANIKAZE-1.5.dist-info/WHEEL
Mensajes_SPARTAN_TANIKAZE-1.5.dist-info/top_level.txt
Mensajes_SPARTAN_TANIKAZE-1.5.dist-info/RECORD
