Metadata-Version: 2.1
Name: Mensajes-SPARTAN-TANIKAZE
Version: 1.5
Summary: Un paquete para saludar y despedir
Home-page: https://www.youtube.com/channel/UCW6SZMRlvJKmH3JGoTZeJoQ
Author: Miguel Gracia
Author-email: miguelgracia1995@hormail.com
Classifier: Environment :: Console
Classifier: Intended Audience :: Developers
Classifier: License :: OSI Approved :: MIT License
Classifier: Operating System :: OS Independent
Classifier: Programming Language :: Python :: 3.10
Classifier: Topic :: Utilities
License-File: LICENSE
Requires-Dist: numpy (>=1.23.4)
